instance_matching/__init__.py
instance_matching/cli.py
instance_matching/evaluator.py
instance_matching/extractor.py
instance_matching/reporter.py
instance_matching/utils.py
instance_matching/visualizer.py
instance_matching/matcher/__init__.py
instance_matching/matcher/gromov_wasserstein.py
instance_matching/matcher/matcher.py
instance_matching/matcher/utils.py
instance_matching/matcher/optimization/__init__.py
instance_matching/matcher/optimization/problem.py
instance_matching/matcher/optimization/solvers.py
instance_matching/matcher/optimization/utils.py
instance_matching-1.0.1.dist-info/licenses/LICENSE
instance_matching-1.0.1.dist-info/METADATA
instance_matching-1.0.1.dist-info/WHEEL
instance_matching-1.0.1.dist-info/entry_points.txt
instance_matching-1.0.1.dist-info/top_level.txt
instance_matching-1.0.1.dist-info/RECORD
