Metadata-Version: 2.4
Name: instance_matching
Version: 1.0.1
Summary: HD-map instance extraction & matching toolkit
Author-email: Jinhwan Jeon <jordan98@kaist.ac.kr>
License: MIT License
Project-URL: Homepage, https://github.com/wjswlsghks98/instance-matching
Project-URL: Source, https://github.com/wjswlsghks98/instance-matching
Project-URL: Issue Tracker, https://github.com/wjswlsghks98/instance-matching/issues
Keywords: hd-map,instance matching,lanelet
Classifier: Development Status :: 3 - Alpha
Classifier: Intended Audience :: Developers
Classifier: License :: OSI Approved :: MIT License
Classifier: Programming Language :: Python :: 3
Classifier: Programming Language :: Python :: 3.9
Classifier: Topic :: Scientific/Engineering :: GIS
Requires-Python: >=3.9
License-File: LICENSE
Requires-Dist: numpy<2.0
Requires-Dist: scipy
Requires-Dist: shapely
Requires-Dist: matplotlib
Requires-Dist: pot
Requires-Dist: cyipopt
Requires-Dist: lanelet2
Requires-Dist: PyYAML
Dynamic: license-file
